odoo10_addon_stock_picking_transfer_lot_autoassign-10.0.1.0.0-py2.7-nspkg.pth
odoo/addons/stock_picking_transfer_lot_autoassign/README.rst
odoo/addons/stock_picking_transfer_lot_autoassign/__init__.py
odoo/addons/stock_picking_transfer_lot_autoassign/__manifest__.py
odoo/addons/stock_picking_transfer_lot_autoassign/i18n/de.po
odoo/addons/stock_picking_transfer_lot_autoassign/i18n/es.po
odoo/addons/stock_picking_transfer_lot_autoassign/i18n/fr.po
odoo/addons/stock_picking_transfer_lot_autoassign/i18n/it.po
odoo/addons/stock_picking_transfer_lot_autoassign/i18n/pt_BR.po
odoo/addons/stock_picking_transfer_lot_autoassign/models/__init__.py
odoo/addons/stock_picking_transfer_lot_autoassign/models/stock_picking.py
odoo/addons/stock_picking_transfer_lot_autoassign/models/stock_picking_type.py
odoo/addons/stock_picking_transfer_lot_autoassign/static/description/icon.png
odoo/addons/stock_picking_transfer_lot_autoassign/tests/__init__.py
odoo/addons/stock_picking_transfer_lot_autoassign/tests/test_stock_picking_transfer_lot_autoassign.py
odoo/addons/stock_picking_transfer_lot_autoassign/views/stock_picking_type_view.xml
odoo10_addon_stock_picking_transfer_lot_autoassign-10.0.1.0.0.dist-info/DESCRIPTION.rst
odoo10_addon_stock_picking_transfer_lot_autoassign-10.0.1.0.0.dist-info/METADATA
odoo10_addon_stock_picking_transfer_lot_autoassign-10.0.1.0.0.dist-info/RECORD
odoo10_addon_stock_picking_transfer_lot_autoassign-10.0.1.0.0.dist-info/WHEEL
odoo10_addon_stock_picking_transfer_lot_autoassign-10.0.1.0.0.dist-info/metadata.json
odoo10_addon_stock_picking_transfer_lot_autoassign-10.0.1.0.0.dist-info/namespace_packages.txt
odoo10_addon_stock_picking_transfer_lot_autoassign-10.0.1.0.0.dist-info/top_level.txt
